{"version": 0.6, "generator": "Overpass API 0.7.62.8 e802775f", "osm3s": {"timestamp_osm_base": "2026-01-04T12:14:30Z", "copyright": "The data included in this document is from www.openstreetmap.org. The data is made available under ODbL."}, "elements": [{"type": "node", "id": 288457748, "lat": 49.4598994, "lon": 15.0172836, "tags": {"name": "Pacov", "name:de": "Patzau", "public_transport": "station", "railway": "station", "source": "uhul:ortofoto", "wikidata": "Q15886973"}}, {"type": "node", "id": 309475007, "lat": 49.3417089, "lon": 14.984291, "tags": {"name": "Chv\u00e1lkov", "operator": "cz:JHMD", "railway": "station", "railway:ref": "745828"}}, {"type": "node", "id": 659899114, "lat": 49.4257356, "lon": 15.1180964, "tags": {"name": "Nov\u00e1 Cerekev", "public_transport": "station", "railway": "station", "wikidata": "Q15886945"}}, {"type": "node", "id": 659910636, "lat": 49.4296444, "lon": 15.0794033, "tags": {"name": "Leskovice", "railway": "halt", "wikidata": "Q18590899", "wikipedia": "cs:Leskovice (\u017eelezni\u010dn\u00ed zast\u00e1vka)"}}, {"type": "node", "id": 659913658, "lat": 49.4379895, "lon": 14.9749254, "tags": {"name": "\u0160impach", "railway": "halt", "wikidata": "Q19401403"}}]}